{"title":"Ch4 Building Hitlers Supergun 720p x264 AAC HDTV MVGroup.org","uid":12819923,"size":1388391078,"categoryP":"video","categoryS":"hd___tv_shows","magnet":"?xt=urn:btih:000bfb20a9ca240c654a3e71a048cf6029ed2723&amp;dn=Ch4+Building+Hitlers+Supergun+720p+x264+AAC+HDTV+MVGroup.org&amp;tr=udp%3A%2F%2Ftracker.leechers-paradise.org%3A6969&amp;tr=udp%3A%2F%2Fzer0day.ch%3A1337&amp;tr=udp%3A%2F%2Fopen.demonii.com%3A1337&amp;tr=udp%3A%2F%2Ftracker.coppersurfer.tk%3A6969&amp;tr=udp%3A%2F%2Fexodus.desync.com%3A6969","seeders":5,"leechers":0,"uploader":"MVGroup","files":1,"time":1448280983,"description":"Building Hitler's Supergun\r\n\r\nWar Documentary hosted by Jim Carter, published by Channel 4 in 2015 - English narration. \nhttp://docuwiki.net/images/4/49/Building-Hitler-s-Supergun-Cover.jpg\r\n\r\nInformation\r\n------------------------------\r\nBy the spring of 1943, for the first time since the beginning of World War II, Hitler was on the back foot. As Allied bombs rained down on German cities, the Fuhrer was determined to hit back. He drew up plans for the biggest gun the world has ever seen: the V-3 Supergun. From its bunker buried deep in a French hillside, this monstrous 25-barrelled cannon was designed to reduce London to rubble, and turn the course of the war back in Hitler's favour. In a race to knock out the supergun, the allies dreamt up their own miracle weapons.\r\n\r\nScreenshots\r\n------------------------------ \nhttp://docuwiki.net/images/7/78/Building-Hitler-s-Supergun-Screen0.jpg \nhttp://docuwiki.net/images/7/7f/Building-Hitler-s-Supergun-Screen1.jpg \nhttp://docuwiki.net/images/5/55/Building-Hitler-s-Supergun-Screen2.jpg \nhttp://docuwiki.net/images/8/85/Building-Hitler-s-Supergun-Screen3.jpg \nhttp://docuwiki.net/images/5/55/Building-Hitler-s-Supergun-Screen4.jpg \nhttp://docuwiki.net/images/2/23/Building-Hitler-s-Supergun-Screen5.jpg \nhttp://docuwiki.net/images/f/fb/Building-Hitler-s-Supergun-Screen6.jpg \nhttp://docuwiki.net/images/1/19/Building-Hitler-s-Supergun-Screen7.jpg \nhttp://docuwiki.net/images/5/59/Building-Hitler-s-Supergun-Screen8.jpg \r\n\r\nTechnical Specs\r\n------------------------------\r\n * Video Codec: x264 CABAC   \r\n * Video Bitrate: CRF 21 (~3760Kbps)\r\n * Video Resolution: 1280x720\r\n * Video Aspect Ratio: 16:9\r\n * Frames Rate: 25 FPS\r\n * Audio Codec: AAC-LC\r\n * Audio Bitrate: Q=0.45 VBR 44.1KHz (~128Kbps)\r\n * Audio Channels: 2\r\n * Run-Time: 47 mins\r\n * Number Of Parts: 1\r\n * Part Size: 1.29 GB\r\n * Source: HDTV\r\n * Subtitles: Merged\r\n\r\nLinks\r\n------------------------------ \nhttp://www.channel4.com/programmes/building-hitlers-supergun","torrent":{"xt":"urn:btih:000bfb20a9ca240c654a3e71a048cf6029ed2723","amp;dn":"Ch4+Building+Hitlers+Supergun+720p+x264+AAC+HDTV+MVGroup.org","amp;tr":["udp%3A%2F%2Ftracker.leechers-paradise.org%3A6969","udp%3A%2F%2Fzer0day.ch%3A1337","udp%3A%2F%2Fopen.demonii.com%3A1337","udp%3A%2F%2Ftracker.coppersurfer.tk%3A6969","udp%3A%2F%2Fexodus.desync.com%3A6969"],"infoHash":"000bfb20a9ca240c654a3e71a048cf6029ed2723","infoHashBuffer":{"type":"Buffer","data":[0,11,251,32,169,202,36,12,101,74,62,113,160,72,207,96,41,237,39,35]},"announce":[],"urlList":[]}}