{"title":"AMERICAN DAD - SEASON 4","uid":4925455,"size":3858006738,"categoryP":"video","categoryS":"tv_shows","magnet":"?xt=urn:btih:01a77f8799685de87e8d3cc3bc619911ed2129f0&amp;dn=AMERICAN+DAD+-+SEASON+4&amp;tr=udp%3A%2F%2Ftracker.openbittorrent.com%3A80&amp;tr=udp%3A%2F%2Fopen.demonii.com%3A1337&amp;tr=udp%3A%2F%2Ftracker.coppersurfer.tk%3A6969&amp;tr=udp%3A%2F%2Fexodus.desync.com%3A6969","seeders":4,"leechers":2,"uploader":"coca2113","files":20,"time":1243826121,"description":"American dad season 4 \n\nepisode 1 - 20\n\n1600 Candles\nThe One That Got Away\nOne Little Word \nChoosy Wives Choose Smith\nEscape from Pearl Bailey\nPulling Double Booty\nPhantom of the Telethon\nChimdale\nStan Time\nFamily Affair\nLive and Let Fry\nRoy Rogers McFreely\nJack's Back\nBar Mitzvah Shuffle\nWife Insurance\nDelorean Story-An\nEvery Which Way But Lose\nWeiner of Our Discontent\nDaddy Queerest\nStan's Night Out","torrent":{"xt":"urn:btih:01a77f8799685de87e8d3cc3bc619911ed2129f0","amp;dn":"AMERICAN+DAD+-+SEASON+4","amp;tr":["udp%3A%2F%2Ftracker.openbittorrent.com%3A80","udp%3A%2F%2Fopen.demonii.com%3A1337","udp%3A%2F%2Ftracker.coppersurfer.tk%3A6969","udp%3A%2F%2Fexodus.desync.com%3A6969"],"infoHash":"01a77f8799685de87e8d3cc3bc619911ed2129f0","infoHashBuffer":{"type":"Buffer","data":[1,167,127,135,153,104,93,232,126,141,60,195,188,97,153,17,237,33,41,240]},"announce":[],"urlList":[]}}