{"title":"Gabbar is Back (2015) Hindi UNTOUCHED CAM - ZippyMovieZ EXCLUSIV","uid":11873715,"size":623968657,"categoryP":"video","categoryS":"movies","magnet":"?xt=urn:btih:0c21c78bbb9abd30049040ba0f3220d282f46622&amp;dn=Gabbar+is+Back+%282015%29+Hindi+UNTOUCHED+CAM+-+ZippyMovieZ+EXCLUSIV&amp;tr=udp%3A%2F%2Ftracker.openbittorrent.com%3A80&amp;tr=udp%3A%2F%2Fopen.demonii.com%3A1337&amp;tr=udp%3A%2F%2Ftracker.coppersurfer.tk%3A6969&amp;tr=udp%3A%2F%2Fexodus.desync.com%3A6969","seeders":5,"leechers":1,"uploader":"desi11","files":2,"time":1430490767,"description":"\n\n &lt;a href=&quot;\nhttp://www.zippymoviez.com/forum/topic/43007-gabbar-is-back-2015-hindi-untouched-cam-zippymoviez-exclusive/&quot; rel=&quot;nofollow&quot; target=&quot;_NEW&quot;&gt;\nhttp://www.zippymoviez.com/forum/topic/43007-gabbar-is-back-2015-hindi-untouched-cam-zippymoviez-exclusive/&lt;/a&gt;","torrent":{"xt":"urn:btih:0c21c78bbb9abd30049040ba0f3220d282f46622","amp;dn":"Gabbar+is+Back+%282015%29+Hindi+UNTOUCHED+CAM+-+ZippyMovieZ+EXCLUSIV","amp;tr":["udp%3A%2F%2Ftracker.openbittorrent.com%3A80","udp%3A%2F%2Fopen.demonii.com%3A1337","udp%3A%2F%2Ftracker.coppersurfer.tk%3A6969","udp%3A%2F%2Fexodus.desync.com%3A6969"],"infoHash":"0c21c78bbb9abd30049040ba0f3220d282f46622","infoHashBuffer":{"type":"Buffer","data":[12,33,199,139,187,154,189,48,4,144,64,186,15,50,32,210,130,244,102,34]},"announce":[],"urlList":[]}}