{"title":"September (Woody Allen, 1987)","uid":3579392,"size":734457856,"categoryP":"video","categoryS":"movies","magnet":"?xt=urn:btih:0d66f94fe1672e6684cba6815dd49d7287892264&amp;dn=September+%28Woody+Allen%2C+1987%29&amp;tr=udp%3A%2F%2Ftracker.openbittorrent.com%3A80&amp;tr=udp%3A%2F%2Fopen.demonii.com%3A1337&amp;tr=udp%3A%2F%2Ftracker.coppersurfer.tk%3A6969&amp;tr=udp%3A%2F%2Fexodus.desync.com%3A6969","seeders":4,"leechers":0,"uploader":"wolfskind","files":1,"time":1166470331,"description":"No warranty for this rip. Seemed o.k. at the first glance. It is ideal for those who want to complete their Woody Allen collection. Got this through Emule and wanted to share it with the Bittorrent community, as the movie was not to be found on any tracker.","torrent":{"xt":"urn:btih:0d66f94fe1672e6684cba6815dd49d7287892264","amp;dn":"September+%28Woody+Allen%2C+1987%29","amp;tr":["udp%3A%2F%2Ftracker.openbittorrent.com%3A80","udp%3A%2F%2Fopen.demonii.com%3A1337","udp%3A%2F%2Ftracker.coppersurfer.tk%3A6969","udp%3A%2F%2Fexodus.desync.com%3A6969"],"infoHash":"0d66f94fe1672e6684cba6815dd49d7287892264","infoHashBuffer":{"type":"Buffer","data":[13,102,249,79,225,103,46,102,132,203,166,129,93,212,157,114,135,137,34,100]},"announce":[],"urlList":[]}}