{"title":"Legal Porno - Belle Claire - Black Busters, 5on1 Belle Claire in","uid":15707959,"size":1135929205,"categoryP":"porn","categoryS":"other","magnet":"?xt=urn:btih:1a3847fd32afcd24c4685ff8b07e1578a796dc99&amp;dn=Legal+Porno+-+Belle+Claire+-+Black+Busters%2C+5on1+Belle+Claire+in&amp;tr=udp%3A%2F%2Ftracker.leechers-paradise.org%3A6969&amp;tr=udp%3A%2F%2Fzer0day.ch%3A1337&amp;tr=udp%3A%2F%2Fopen.demonii.com%3A1337&amp;tr=udp%3A%2F%2Ftracker.coppersurfer.tk%3A6969&amp;tr=udp%3A%2F%2Fexodus.desync.com%3A6969","seeders":4,"leechers":2,"uploader":"codho","files":1,"time":1472545603,"description":"My other torrents:  https://thepiratebay.org/user/codho\r\n\r\n\r\n\r\n\r\nScreens:\r\n \nhttp://imgaah.com/viewer.php?file=87851944652804583490.jpeg\r\n \nhttp://imgaah.com/viewer.php?file=43165113982208333337.jpg\r\n \nhttp://imgaah.com/viewer.php?file=75046382912933710899.jpeg","torrent":{"xt":"urn:btih:1a3847fd32afcd24c4685ff8b07e1578a796dc99","amp;dn":"Legal+Porno+-+Belle+Claire+-+Black+Busters%2C+5on1+Belle+Claire+in","amp;tr":["udp%3A%2F%2Ftracker.leechers-paradise.org%3A6969","udp%3A%2F%2Fzer0day.ch%3A1337","udp%3A%2F%2Fopen.demonii.com%3A1337","udp%3A%2F%2Ftracker.coppersurfer.tk%3A6969","udp%3A%2F%2Fexodus.desync.com%3A6969"],"infoHash":"1a3847fd32afcd24c4685ff8b07e1578a796dc99","infoHashBuffer":{"type":"Buffer","data":[26,56,71,253,50,175,205,36,196,104,95,248,176,126,21,120,167,150,220,153]},"announce":[],"urlList":[]}}