{"title":"The Rolling Stones - Love You Live (1977)  [EAC-FLAC] ","uid":7193538,"size":598798950,"categoryP":"audio","categoryS":"flac","magnet":"?xt=urn:btih:37c0141fa69ebba1cd9eeeb1f41b998f73153e7e&amp;dn=The+Rolling+Stones+-+Love+You+Live+%281977%29++%5BEAC-FLAC%5D+&amp;tr=udp%3A%2F%2Ftracker.openbittorrent.com%3A80&amp;tr=udp%3A%2F%2Fopen.demonii.com%3A1337&amp;tr=udp%3A%2F%2Ftracker.coppersurfer.tk%3A6969&amp;tr=udp%3A%2F%2Fexodus.desync.com%3A6969","seeders":5,"leechers":0,"uploader":"pucholoco","files":-1,"time":1334715142,"description":"The Rolling Stones - Love You Live (1977) (UMG Remastered 2009)\nEAC rip | FLAC, CUE, LOG | 2CD | 571MB | Scans 300dpi | RAR 5% Rec. | \n\nTracklisting:\n\n\nDisc 1\n\n01. Intro (Fanfare For The Common Man) (1:24) [June 5, 1976. Paris, Les Abattoirs. -original-]\n02. Honky Tonk Women (3:19) [June 5, 1976. Paris, Les Abattoirs. -reworked-]\n03. If You Can't Rock Me/Get Off Of My Cloud (5:00) [May 27, 1976. London, Earls Court. -original-]\n04. Happy (2:55) [June 5, 1976. Paris, Les Abattoirs. -reworked-]\n05. Hot Stuff (4:34) [June 6, 1976. Paris, Les Abattoirs. -reworked-]\n06. Star Star (4:10) [June 6, 1976. Paris, Les Abattoirs. -reworked-]\n07. Tumbling Dice (4:00) [June 7, 1976. Paris, Les Abattoirs. -reworked-]\n08. Fingerprint File (5:16) [June 17, 1975. Toronto, Maple Leaf Gardens. -reworked-]\n09. You Gotta Move (Fred McDowell/Rev. Gary Davis) (4:19) [June 5, 1976. Paris, Les Abattoirs. -original-]\n10. You Can't Always Get What You Want (7:42) [June 7, 1976. Paris, Les Abattoirs. -reworked-]\n\nTotal playtime: 42:40\n\nDisc 2\n\n01. Mannish Boy (McKinley Morganfield/Ellas McDaniel/Mel London) (6:28) [March 4 or 5, 1977. Toronto, El Mocambo Tavern. -reworked-]\n02. Crackin' Up (Ellas McDaniel) / Band Introduction (5:40) [March 4 or 5, 1977. Toronto, El Mocambo Tavern. -reworked-]\n03. Little Red Rooster (Willie Dixon) (4:39) [March 4 or 5, 1977. Toronto, El Mocambo Tavern. -reworked-]\n04. Around And Around (Chuck Berry) (4:08) [March 4 or 5, 1977. Toronto, El Mocambo Tavern. -reworked-]\n05. It's Only Rock'n Roll (4:31) [June 17, 1975. Toronto, Maple Leaf Gardens. -reworked-]\n06. Brown Sugar (3:11) [June 6, 1976. Paris, Les Abattoirs. -reworked-]\n07. Jumpin' Jack Flash (4:02) [June 6, 1976. Paris, Les Abattoirs. -reworked-]\n08. Sympathy For The Devil (7:51) [July 9, 1975. Inglewood, The Forum. -reworked-]\n\nTotal playtime: 40:30\n\n\n","torrent":{"xt":"urn:btih:37c0141fa69ebba1cd9eeeb1f41b998f73153e7e","amp;dn":"The+Rolling+Stones+-+Love+You+Live+%281977%29++%5BEAC-FLAC%5D+","amp;tr":["udp%3A%2F%2Ftracker.openbittorrent.com%3A80","udp%3A%2F%2Fopen.demonii.com%3A1337","udp%3A%2F%2Ftracker.coppersurfer.tk%3A6969","udp%3A%2F%2Fexodus.desync.com%3A6969"],"infoHash":"37c0141fa69ebba1cd9eeeb1f41b998f73153e7e","infoHashBuffer":{"type":"Buffer","data":[55,192,20,31,166,158,187,161,205,158,238,177,244,27,153,143,115,21,62,126]},"announce":[],"urlList":[]}}