{"title":"Lynda.com - Up and Running with CakePHP","uid":8992448,"size":328243774,"categoryP":"video","categoryS":"other","magnet":"?xt=urn:btih:39c10a1773c952b7c9d60ddd7310f64555316dac&amp;dn=Lynda.com+-+Up+and+Running+with+CakePHP&amp;tr=udp%3A%2F%2Ftracker.openbittorrent.com%3A80&amp;tr=udp%3A%2F%2Fopen.demonii.com%3A1337&amp;tr=udp%3A%2F%2Ftracker.coppersurfer.tk%3A6969&amp;tr=udp%3A%2F%2Fexodus.desync.com%3A6969","seeders":5,"leechers":1,"uploader":"sigor10","files":28,"time":1380818392,"description":"Speed up your development with CakePHP, the popular open-source PHP framework. In this course, author Jon Peck builds a magazine cataloging system while explaining how to work with the Model-View-Controller (MVC) development pattern.\n\nThe course demonstrates how to install and configure CakePHP, describing the layout and components. Then, leveraging the Bake console, Jon shows how to generate and customize code, and explores form validation, database persistence, and even image uploads. By developing a complete, functional application, you'll have the foundation you need to build your own applications with CakePHP.\n\nTopics include:\n\n    What is CakePHP?\n    Installing and configuring CakePHP\n    Generating a model with Bake\n    Linking models together\n    Generating a controller\n    Saving a model from the controller\n    Displaying a model with a view\n    Debugging a failed save\n    Using helpers to generate HTML\n    Uploading files and displaying images","torrent":{"xt":"urn:btih:39c10a1773c952b7c9d60ddd7310f64555316dac","amp;dn":"Lynda.com+-+Up+and+Running+with+CakePHP","amp;tr":["udp%3A%2F%2Ftracker.openbittorrent.com%3A80","udp%3A%2F%2Fopen.demonii.com%3A1337","udp%3A%2F%2Ftracker.coppersurfer.tk%3A6969","udp%3A%2F%2Fexodus.desync.com%3A6969"],"infoHash":"39c10a1773c952b7c9d60ddd7310f64555316dac","infoHashBuffer":{"type":"Buffer","data":[57,193,10,23,115,201,82,183,201,214,13,221,115,16,246,69,85,49,109,172]},"announce":[],"urlList":[]}}