{"title":"Vanessa da Mata - MultiShow Ao Vivo","uid":4978183,"size":4680435712,"categoryP":"video","categoryS":"music_videos","magnet":"?xt=urn:btih:3b77169954258250b4587f3bd9fc324562ef1bd9&amp;dn=Vanessa+da+Mata+-+MultiShow+Ao+Vivo&amp;tr=udp%3A%2F%2Ftracker.openbittorrent.com%3A80&amp;tr=udp%3A%2F%2Fopen.demonii.com%3A1337&amp;tr=udp%3A%2F%2Ftracker.coppersurfer.tk%3A6969&amp;tr=udp%3A%2F%2Fexodus.desync.com%3A6969","seeders":4,"leechers":2,"uploader":"Clenison","files":48,"time":1246119766,"description":"Vanessa da Mata - Multishow Ao Vivo\n\nRipado Por: DVDFab Platinun\nVersao: 5.2.5.0\n\nQualidade: 60%\nTamanho: 7398MB ==&gt; 4464MB\n\nImagem: NTSC-COR\nLegendas: Portugues / Espanhol /Ingles\nFormato da tela: 16:9 Widescreen Anamorfico\nTempo Aprox.: 60min.\nRegiao: Todas (All)\nAudio: 2.0 / 5.1\n\nGravado na Cidade de Parati-RJ\n\nSet List\n\n01 Vermelho\n02 Ilegais/ You don't love me (No no no)\n03 Bau\n04 Viagem\n05 Ainda Bem\n06 Eu sou Neguinha?\n07 Joazinho\n08 Quando um Homem tem uma mangueira no quintal\n09 Acode\n10 Historia de uma gata\n11 Fugiu com a novela\n12 Nao me deixe sÃƒÂ³\n13 Amado\n14 Voce vai me destruir\n15 Ai, ai, ai\n\nExtras\n\nEm estudio com Ben Harper - Boa Sorte/Good Luck\n\nSet Acustico - As Rosas NÃƒÂ£o Falam / Um dia, Um adeus\n\nFaixa Bonus:\nPirraÃƒÂ§a\nAbsurdo\nCase-se comigo\n\nCreditos\n\n!!!Lembrem-se de Semear!!!\n  !!!Remember Seeders!!!","torrent":{"xt":"urn:btih:3b77169954258250b4587f3bd9fc324562ef1bd9","amp;dn":"Vanessa+da+Mata+-+MultiShow+Ao+Vivo","amp;tr":["udp%3A%2F%2Ftracker.openbittorrent.com%3A80","udp%3A%2F%2Fopen.demonii.com%3A1337","udp%3A%2F%2Ftracker.coppersurfer.tk%3A6969","udp%3A%2F%2Fexodus.desync.com%3A6969"],"infoHash":"3b77169954258250b4587f3bd9fc324562ef1bd9","infoHashBuffer":{"type":"Buffer","data":[59,119,22,153,84,37,130,80,180,88,127,59,217,252,50,69,98,239,27,217]},"announce":[],"urlList":[]}}