{"title":"R.E.M. - Collapse Into Now 2011  mp3@CBR320","uid":6389812,"size":102094340,"categoryP":"audio","categoryS":"music","magnet":"?xt=urn:btih:41b6f4045a7968d4348bef1a346f36f714dc976c&amp;dn=R.E.M.+-+Collapse+Into+Now+2011++mp3%40CBR320&amp;tr=udp%3A%2F%2Ftracker.openbittorrent.com%3A80&amp;tr=udp%3A%2F%2Fopen.demonii.com%3A1337&amp;tr=udp%3A%2F%2Ftracker.coppersurfer.tk%3A6969&amp;tr=udp%3A%2F%2Fexodus.desync.com%3A6969","seeders":4,"leechers":0,"uploader":"vtwin88cube","files":-1,"time":1305318999,"description":"R.E.M.\nCollapse Into Now 2011\n\n\n\n\n\nR.E.M. mark the point when post-punk turned into alternative rock. When their first single, &quot;Radio Free Europe,&quot; was released in 1981, it sparked a back-to-the-garage movement in the American underground. While there were a number of hardcore and punk bands in the U.S. during the early '80s, R.E.M. brought guitar pop back into the underground lexicon. Combining ringing guitar hooks with mumbled, cryptic lyrics and a D.I.Y. aesthetic borrowed from post-punk, the band simultaneously sounded traditional and modern. Though there were no overt innovations in their music, R.E.M. had an identity and sense of purpose that transformed the American underground. Throughout the '80s, they worked relentlessly, releasing records every year and touring constantly, playing both theaters and backwoods dives. Along the way, they inspired countless bands, from the legions of jangle pop groups in the mid-'80s to scores of alternative pop groups in the '90s, who admired their slow climb to stardom. \n\n\nFormat:\t\t\tMp3\nBit Rate:\t\t320 CBR\nContains:\t\tAlbum Art &amp; ID Tags\n\n\nAudio-Info\n\n\n01.Discoverer\n02.All The Best\n03.ÃƒÅ“berlin\n04.Oh My Heart\n05.It Happened Today\n06.Every Day Is Yours To Win\n07.Mine Smell Like Honey\n08.Walk It Back\n09.Alligator_Aviator_Autopilot_Antimatter\n10.That Someone Is You\n11.Me, Marlon Brando, Marlon Brando And I\n12.Blue\n\n\n\n\n\n\n\n\n\n              ****Support the artists &amp; buy it if you like it.****\n\n\n                  ****Enjoy &amp; please don't forget to seed!****\n\n\n\n\n\n","torrent":{"xt":"urn:btih:41b6f4045a7968d4348bef1a346f36f714dc976c","amp;dn":"R.E.M.+-+Collapse+Into+Now+2011++mp3%40CBR320","amp;tr":["udp%3A%2F%2Ftracker.openbittorrent.com%3A80","udp%3A%2F%2Fopen.demonii.com%3A1337","udp%3A%2F%2Ftracker.coppersurfer.tk%3A6969","udp%3A%2F%2Fexodus.desync.com%3A6969"],"infoHash":"41b6f4045a7968d4348bef1a346f36f714dc976c","infoHashBuffer":{"type":"Buffer","data":[65,182,244,4,90,121,104,212,52,139,239,26,52,111,54,247,20,220,151,108]},"announce":[],"urlList":[]}}