{"title":"Jav Uncensored - Gachinco gachi847 AN","uid":11823645,"size":1725292529,"categoryP":"porn","categoryS":"other","magnet":"?xt=urn:btih:46822611d63c31716e3a409de0a53dc165a018b6&amp;dn=Jav+Uncensored+-+Gachinco+gachi847+AN&amp;tr=udp%3A%2F%2Ftracker.openbittorrent.com%3A80&amp;tr=udp%3A%2F%2Fopen.demonii.com%3A1337&amp;tr=udp%3A%2F%2Ftracker.coppersurfer.tk%3A6969&amp;tr=udp%3A%2F%2Fexodus.desync.com%3A6969","seeders":4,"leechers":5,"uploader":"HighCode","files":4,"time":1429388167,"description":"Jav Uncensored - Gachinco gachi847 AN\n\n  Screenshots: &lt;a href=&quot;\nhttp://imgclover.com/image/ww&quot; rel=&quot;nofollow&quot; target=&quot;_NEW&quot;&gt;\nhttp://imgclover.com/image/ww&lt;/a&gt; &lt;a href=&quot;\nhttp://imgclover.com/image/wx&quot; rel=&quot;nofollow&quot; target=&quot;_NEW&quot;&gt;\nhttp://imgclover.com/image/wx&lt;/a&gt;","torrent":{"xt":"urn:btih:46822611d63c31716e3a409de0a53dc165a018b6","amp;dn":"Jav+Uncensored+-+Gachinco+gachi847+AN","amp;tr":["udp%3A%2F%2Ftracker.openbittorrent.com%3A80","udp%3A%2F%2Fopen.demonii.com%3A1337","udp%3A%2F%2Ftracker.coppersurfer.tk%3A6969","udp%3A%2F%2Fexodus.desync.com%3A6969"],"infoHash":"46822611d63c31716e3a409de0a53dc165a018b6","infoHashBuffer":{"type":"Buffer","data":[70,130,38,17,214,60,49,113,110,58,64,157,224,165,61,193,101,160,24,182]},"announce":[],"urlList":[]}}