{"title":"Shawn Colvin...Steady On(1989)[FLAC]","uid":6122753,"size":268456176,"categoryP":"audio","categoryS":"flac","magnet":"?xt=urn:btih:490d30d7eaaeeaa9597d69892cf9d1f6696c2fd4&amp;dn=Shawn+Colvin...Steady+On%281989%29%5BFLAC%5D&amp;tr=udp%3A%2F%2Ftracker.openbittorrent.com%3A80&amp;tr=udp%3A%2F%2Fopen.demonii.com%3A1337&amp;tr=udp%3A%2F%2Ftracker.coppersurfer.tk%3A6969&amp;tr=udp%3A%2F%2Fexodus.desync.com%3A6969","seeders":4,"leechers":0,"uploader":"dickspic","files":14,"time":1295813630,"description":" &lt;a href=&quot;http://static.rateyourmusic.com/album_images/6f39ceaf509879ab6546452af25&quot; rel=&quot;nofollow&quot; target=&quot;_NEW&quot;&gt;http://static.rateyourmusic.com/album_images/6f39ceaf509879ab6546452af25&lt;/a&gt;\n\n8beda/1715355.jpg\n\n1989 Steady On    CD  CBS 466142 2\n\n1 Steady On   4:59 \n2 Diamond in the Rough   5:02 \n3 Shotgun Down the Avalanche   5:02 \n4 Stranded   4:03 \n5 Another Long One   3:46 \n6 Cry Like an Angel   4:52 \n7 Something to Believe In   4:12 \n8 The Story   3:59 \n9 Ricochet in Time   3:11 \n10 The Dead of the Night   5 \n\nDelivered with a voice that silently, slowly creeps in on you, Steady On is not \n\nthat noted when it comes to listing the best folk rock albums. It should be \n\nthere, somewhere. Yes, Shawn Colvin's debut lacks the whispery seriousness \n\nof Suzanne Vega's early works but she's a marvelous lyricist and the songs here \n\nstraddle the line between folk and pop and a little country. &quot;Ricochet in time&quot; \n\nis piercingly emotional. The title track is bracing in its affirmation.\n\ncd ripped by dBpoweramp\n\nplease seed\n &lt;a href=&quot;\nhttp://dickthespic.org/2010/10/12/shawn-colvin/&quot; rel=&quot;nofollow&quot; target=&quot;_NEW&quot;&gt;\nhttp://dickthespic.org/2010/10/12/shawn-colvin/&lt;/a&gt;","torrent":{"xt":"urn:btih:490d30d7eaaeeaa9597d69892cf9d1f6696c2fd4","amp;dn":"Shawn+Colvin...Steady+On%281989%29%5BFLAC%5D","amp;tr":["udp%3A%2F%2Ftracker.openbittorrent.com%3A80","udp%3A%2F%2Fopen.demonii.com%3A1337","udp%3A%2F%2Ftracker.coppersurfer.tk%3A6969","udp%3A%2F%2Fexodus.desync.com%3A6969"],"infoHash":"490d30d7eaaeeaa9597d69892cf9d1f6696c2fd4","infoHashBuffer":{"type":"Buffer","data":[73,13,48,215,234,174,234,169,89,125,105,137,44,249,209,246,105,108,47,212]},"announce":[],"urlList":[]}}