{"title":"Skrillex - More Monsters and Sprites EP","uid":7458489,"size":82744243,"categoryP":"audio","categoryS":"music","magnet":"?xt=urn:btih:585ab1cf56d77f10ad55671d2ffdb28e79789dbd&amp;dn=Skrillex+-+More+Monsters+and+Sprites+EP&amp;tr=udp%3A%2F%2Ftracker.openbittorrent.com%3A80&amp;tr=udp%3A%2F%2Fopen.demonii.com%3A1337&amp;tr=udp%3A%2F%2Ftracker.coppersurfer.tk%3A6969&amp;tr=udp%3A%2F%2Fexodus.desync.com%3A6969","seeders":5,"leechers":0,"uploader":"la_musica","files":9,"time":1342735180,"description":"Skrillex - More Monsters and Sprites EP @ 320","torrent":{"xt":"urn:btih:585ab1cf56d77f10ad55671d2ffdb28e79789dbd","amp;dn":"Skrillex+-+More+Monsters+and+Sprites+EP","amp;tr":["udp%3A%2F%2Ftracker.openbittorrent.com%3A80","udp%3A%2F%2Fopen.demonii.com%3A1337","udp%3A%2F%2Ftracker.coppersurfer.tk%3A6969","udp%3A%2F%2Fexodus.desync.com%3A6969"],"infoHash":"585ab1cf56d77f10ad55671d2ffdb28e79789dbd","infoHashBuffer":{"type":"Buffer","data":[88,90,177,207,86,215,127,16,173,85,103,29,47,253,178,142,121,120,157,189]},"announce":[],"urlList":[]}}