{"title":"DigitalPlayground Aria Alexander - Suicide Squad XXX Parody","uid":15451907,"size":390048627,"categoryP":"porn","categoryS":"movies","magnet":"?xt=urn:btih:6333b5fb6b76f7a64d21c017f346ab56a264a9ce&amp;dn=DigitalPlayground+Aria+Alexander+-+Suicide+Squad+XXX+Parody&amp;tr=udp%3A%2F%2Ftracker.leechers-paradise.org%3A6969&amp;tr=udp%3A%2F%2Fzer0day.ch%3A1337&amp;tr=udp%3A%2F%2Fopen.demonii.com%3A1337&amp;tr=udp%3A%2F%2Ftracker.coppersurfer.tk%3A6969&amp;tr=udp%3A%2F%2Fexodus.desync.com%3A6969","seeders":4,"leechers":1,"uploader":"SudoSu","files":1,"time":1469948182,"description":"http://youpornbook.com\r\n\r\n-------------------------\r\n ... : Screenshots : ... \r\n-------------------------\r\n \nhttp://imgscorpion.com/?v=261866 \nhttp://imgscorpion.com/?v=472762\r\n\r\n\r\nMore exclusive porn at:  https://thepiratebay.se/user/SudoSu/","torrent":{"xt":"urn:btih:6333b5fb6b76f7a64d21c017f346ab56a264a9ce","amp;dn":"DigitalPlayground+Aria+Alexander+-+Suicide+Squad+XXX+Parody","amp;tr":["udp%3A%2F%2Ftracker.leechers-paradise.org%3A6969","udp%3A%2F%2Fzer0day.ch%3A1337","udp%3A%2F%2Fopen.demonii.com%3A1337","udp%3A%2F%2Ftracker.coppersurfer.tk%3A6969","udp%3A%2F%2Fexodus.desync.com%3A6969"],"infoHash":"6333b5fb6b76f7a64d21c017f346ab56a264a9ce","infoHashBuffer":{"type":"Buffer","data":[99,51,181,251,107,118,247,166,77,33,192,23,243,70,171,86,162,100,169,206]},"announce":[],"urlList":[]}}