{"title":"Cant.Pay.Well.Take.It.Away.S04E14.480p.x264-mSD","uid":15879355,"size":294203548,"categoryP":"video","categoryS":"tv_shows","magnet":"?xt=urn:btih:7d680686073fecdf3c39ffa4294a0864afd95f39&amp;dn=Cant.Pay.Well.Take.It.Away.S04E14.480p.x264-mSD&amp;tr=udp%3A%2F%2Ftracker.leechers-paradise.org%3A6969&amp;tr=udp%3A%2F%2Fzer0day.ch%3A1337&amp;tr=udp%3A%2F%2Fopen.demonii.com%3A1337&amp;tr=udp%3A%2F%2Ftracker.coppersurfer.tk%3A6969&amp;tr=udp%3A%2F%2Fexodus.desync.com%3A6969","seeders":5,"leechers":3,"uploader":"TvTeam","files":7,"time":1474574561,"description":"Torrent from:\r\n~~~~~~~~~~~~ \nhttps://www.torrenting.com\r\n\r\nJoin us and become part of the BIG family! Yarrrrrrrrrrrrrr!!!","torrent":{"xt":"urn:btih:7d680686073fecdf3c39ffa4294a0864afd95f39","amp;dn":"Cant.Pay.Well.Take.It.Away.S04E14.480p.x264-mSD","amp;tr":["udp%3A%2F%2Ftracker.leechers-paradise.org%3A6969","udp%3A%2F%2Fzer0day.ch%3A1337","udp%3A%2F%2Fopen.demonii.com%3A1337","udp%3A%2F%2Ftracker.coppersurfer.tk%3A6969","udp%3A%2F%2Fexodus.desync.com%3A6969"],"infoHash":"7d680686073fecdf3c39ffa4294a0864afd95f39","infoHashBuffer":{"type":"Buffer","data":[125,104,6,134,7,63,236,223,60,57,255,164,41,74,8,100,175,217,95,57]},"announce":[],"urlList":[]}}