{"title":"Braveheart.1995.1080p.x264.DTS.4AUDIO-WAF","uid":5899317,"size":13249541931,"categoryP":"video","categoryS":"hd___movies","magnet":"?xt=urn:btih:8a5d490f502b1ecc2d5208b53a9f51f02a0b035a&amp;dn=Braveheart.1995.1080p.x264.DTS.4AUDIO-WAF&amp;tr=udp%3A%2F%2Ftracker.openbittorrent.com%3A80&amp;tr=udp%3A%2F%2Fopen.demonii.com%3A1337&amp;tr=udp%3A%2F%2Ftracker.coppersurfer.tk%3A6969&amp;tr=udp%3A%2F%2Fexodus.desync.com%3A6969","seeders":4,"leechers":1,"uploader":"sadbawang","files":-1,"time":1287625491,"description":"***************************************************************************\n\n Braveheart (1995)\n\n***************************************************************************\n\n[RELEASE INFORMATION]\n\n REL FILES **** : Braveheart.1995.1080p.x264.DTS.4AUDIO-WAF.mkv (12.3 GiB)\n SOURCE ******* : Blue_Ray\n RIPPER ******* : Team_WAF\n REL DATE ***** : 2009-09-10\n RUNTIME ****** : 02:57:43.168\n VIDEO INFO *** : x264-core 67 r1165 6841c5e @ 7,536 Kbps Avg\n FRAME RATE *** : 23.976 fps\n RESOLUTION *** : 1920 x 816 (2.353 : 1)\n AUDIO 1 INFO * : DTS 3/2.1 CH @ 1536 Kbps (English)\n AUDIO 2 INFO * : AC3 3/2.1 CH @ 448 Kbps (Chinese)\n AUDIO 3 INFO * : AC3 2/0 CH @ 192 Kbps (Chinese)\n AUDIO 4 INFO * : AC3 2/0 CH @ 224 Kbps (Commentary)\n LANGUAGE ***** : English\n SUBTITLE ***** : English\n\n***************************************************************************\n\n[RELEASE NOTE]\n\n Thanks http://www.5iwaf.com/ and http://www.wafhd.com/\n\n***************************************************************************","torrent":{"xt":"urn:btih:8a5d490f502b1ecc2d5208b53a9f51f02a0b035a","amp;dn":"Braveheart.1995.1080p.x264.DTS.4AUDIO-WAF","amp;tr":["udp%3A%2F%2Ftracker.openbittorrent.com%3A80","udp%3A%2F%2Fopen.demonii.com%3A1337","udp%3A%2F%2Ftracker.coppersurfer.tk%3A6969","udp%3A%2F%2Fexodus.desync.com%3A6969"],"infoHash":"8a5d490f502b1ecc2d5208b53a9f51f02a0b035a","infoHashBuffer":{"type":"Buffer","data":[138,93,73,15,80,43,30,204,45,82,8,181,58,159,81,240,42,11,3,90]},"announce":[],"urlList":[]}}