{"title":"The Leftovers S01E02 1080p HDTV [G2G].mp4","uid":10502837,"size":1296439241,"categoryP":"video","categoryS":"hd___tv_shows","magnet":"?xt=urn:btih:8d0780d3ccc46242dd59cf229d94577d7548ff85&amp;dn=The+Leftovers+S01E02+1080p+HDTV+%5BG2G%5D.mp4&amp;tr=udp%3A%2F%2Ftracker.openbittorrent.com%3A80&amp;tr=udp%3A%2F%2Fopen.demonii.com%3A1337&amp;tr=udp%3A%2F%2Ftracker.coppersurfer.tk%3A6969&amp;tr=udp%3A%2F%2Fexodus.desync.com%3A6969","seeders":5,"leechers":0,"uploader":"G2GFM","files":-1,"time":1404724075,"description":"Watch and Download All the New Movies and TV Shows on Our Website.\n &lt;a href=&quot;\nhttp://g2g.fm&quot; rel=&quot;nofollow&quot; target=&quot;_NEW&quot;&gt;\nhttp://g2g.fm&lt;/a&gt;\n\n------------------------------------------\n\nGenre: Drama | Fantasy | Mystery\n\n[IMDb] Rating: 7.9/10\n\nViewers: ~1,700,000\n\nSize: ~1.5 GB\n\nFormat: MP4\n\nResolution: 1920x1080\n\nRuntime: ~60min\n\nAirs on: HBO\n\nEpisode Title: Penguin One, Us Zero\n\nAir Date: July 6, 2014\n\nAirs: Sundays at 10:00 PM (EST)\n\nCreator: Damon Lindelof\n\nStars: Michael Gaston, Justin Theroux and Frank Harts\n\nSynopsis: Revolves around mysterious disappearances, world-wide, and specifically follows a group of people who are left behind in the suburban community of Mapleton. They must begin to rebuild their lives after the loss of more than 100 people.","torrent":{"xt":"urn:btih:8d0780d3ccc46242dd59cf229d94577d7548ff85","amp;dn":"The+Leftovers+S01E02+1080p+HDTV+%5BG2G%5D.mp4","amp;tr":["udp%3A%2F%2Ftracker.openbittorrent.com%3A80","udp%3A%2F%2Fopen.demonii.com%3A1337","udp%3A%2F%2Ftracker.coppersurfer.tk%3A6969","udp%3A%2F%2Fexodus.desync.com%3A6969"],"infoHash":"8d0780d3ccc46242dd59cf229d94577d7548ff85","infoHashBuffer":{"type":"Buffer","data":[141,7,128,211,204,196,98,66,221,89,207,34,157,148,87,125,117,72,255,133]},"announce":[],"urlList":[]}}