{"title":"Formula.1.2014.Abu.Dhabi.Grand.Prix.Qualifying.BBC-SM.mp4","uid":11541796,"size":893863204,"categoryP":"video","categoryS":"tv_shows","magnet":"?xt=urn:btih:9c68a1535bd66ffe25f96604c8a4d625c315b6e6&amp;dn=Formula.1.2014.Abu.Dhabi.Grand.Prix.Qualifying.BBC-SM.mp4&amp;tr=udp%3A%2F%2Ftracker.openbittorrent.com%3A80&amp;tr=udp%3A%2F%2Fopen.demonii.com%3A1337&amp;tr=udp%3A%2F%2Ftracker.coppersurfer.tk%3A6969&amp;tr=udp%3A%2F%2Fexodus.desync.com%3A6969","seeders":4,"leechers":0,"uploader":"tonyisaac","files":1,"time":1416675366,"description":"Formula.1.2014.Abu.Dhabi.Grand.Prix.Qualifying.BBC-SM\n \nFormat            : Flash Video at 925 Kbps\nLength            : 852 MiB for 2h 8mn 48s 0ms\n\nVideo #0          : AVC\nAspect            : 704 x 396 (1.778) at 25.000 fps\n\nAudio #0          : AAC\nInfos             : 2 channels, 48.0 KHz\n\n  Suzi Perry introduces live coverage of qualifying for the final race of\nan enthralling season in F1 at Yas Marina for the Abu Dhabi Grand Prix","torrent":{"xt":"urn:btih:9c68a1535bd66ffe25f96604c8a4d625c315b6e6","amp;dn":"Formula.1.2014.Abu.Dhabi.Grand.Prix.Qualifying.BBC-SM.mp4","amp;tr":["udp%3A%2F%2Ftracker.openbittorrent.com%3A80","udp%3A%2F%2Fopen.demonii.com%3A1337","udp%3A%2F%2Ftracker.coppersurfer.tk%3A6969","udp%3A%2F%2Fexodus.desync.com%3A6969"],"infoHash":"9c68a1535bd66ffe25f96604c8a4d625c315b6e6","infoHashBuffer":{"type":"Buffer","data":[156,104,161,83,91,214,111,254,37,249,102,4,200,164,214,37,195,21,182,230]},"announce":[],"urlList":[]}}