{"title":"Shawn Mullins Discography","uid":4710158,"size":745044397,"categoryP":"audio","categoryS":"music","magnet":"?xt=urn:btih:9f50db5fbdf73e5fd40a9b7378c5e5127239b758&amp;dn=Shawn+Mullins+Discography&amp;tr=udp%3A%2F%2Ftracker.openbittorrent.com%3A80&amp;tr=udp%3A%2F%2Fopen.demonii.com%3A1337&amp;tr=udp%3A%2F%2Ftracker.coppersurfer.tk%3A6969&amp;tr=udp%3A%2F%2Fexodus.desync.com%3A6969","seeders":4,"leechers":2,"uploader":"MasonJT","files":135,"time":1233988546,"description":"Missing Jeff's Last Dance Vol 1+2\n\n[1992] Better Days\n[1994] Big Blue Sky\n[1996] Eggshells\n[1998] Soul's Core\n[1999] The First Ten Years\n[2000] Beneath The Sun\n[2003] The Essential Shawn Mullins\n[2006] 9th Ward Pickin' Parlor\n[2008] Honeydew\n[2008] Live At The Variety Playhouse","torrent":{"xt":"urn:btih:9f50db5fbdf73e5fd40a9b7378c5e5127239b758","amp;dn":"Shawn+Mullins+Discography","amp;tr":["udp%3A%2F%2Ftracker.openbittorrent.com%3A80","udp%3A%2F%2Fopen.demonii.com%3A1337","udp%3A%2F%2Ftracker.coppersurfer.tk%3A6969","udp%3A%2F%2Fexodus.desync.com%3A6969"],"infoHash":"9f50db5fbdf73e5fd40a9b7378c5e5127239b758","infoHashBuffer":{"type":"Buffer","data":[159,80,219,95,189,247,62,95,212,10,155,115,120,197,229,18,114,57,183,88]},"announce":[],"urlList":[]}}