{"title":"Oblivion (2013) 3D BrRip x264 - MHDS","uid":8741930,"size":2116834298,"categoryP":"video","categoryS":"3d","magnet":"?xt=urn:btih:bf7fec6d11ea3a6fe5dee3014a51e22999ae355f&amp;dn=Oblivion+%282013%29+3D+BrRip+x264+-+MHDS&amp;tr=udp%3A%2F%2Ftracker.openbittorrent.com%3A80&amp;tr=udp%3A%2F%2Fopen.demonii.com%3A1337&amp;tr=udp%3A%2F%2Ftracker.coppersurfer.tk%3A6969&amp;tr=udp%3A%2F%2Fexodus.desync.com%3A6969","seeders":4,"leechers":1,"uploader":"kickUploader","files":-1,"time":1374812298,"description":"-------------------------------------------------------------------------------\n\n-------------------------------------------------------------------------------\n\n\nGet all MHDS newest releases first at\n\nAlso there you will find a list of upcoming uploads, and an effective movie search.\n\n\n-------------------------------------------------------------------------------\n\n-------------------------------------------------------------------------------\n\n\n &lt;a href=&quot;\nhttp://www.imdb.com/title/tt1483013/&quot; rel=&quot;nofollow&quot; target=&quot;_NEW&quot;&gt;\nhttp://www.imdb.com/title/tt1483013/&lt;/a&gt;\n\n\nIMDB RATING: 7.1\n\nFORMAT.......................: MP4\nCODEC........................: X264\nGENRE........................: Action|fiction\nFILE SIZE....................: 1.97 GB\nRESOLUTION...................: 1920*808\nFRAME RATE...................: 23.976 fps\nLANGUAGE.....................: English\nSUBTITLES....................: English\nRUNTIME......................: 124 mins\n\n\n\nSynopsis: One of the few remaining drone repairmen assigned to Earth, its surface devastated after decades of war with the alien Scavs, discovers a crashed spacecraft with contents that bring into question everything he believed about the war, and may even put the fate of mankind in his hands.\n &lt;a href=&quot;\nhttp://i.imgur.com/yv2TWUP.jpg&quot; rel=&quot;nofollow&quot; target=&quot;_NEW&quot;&gt;\nhttp://i.imgur.com/yv2TWUP.jpg&lt;/a&gt;\n &lt;a href=&quot;\nhttp://i.imgur.com/Eqjr2ro.jpg&quot; rel=&quot;nofollow&quot; target=&quot;_NEW&quot;&gt;\nhttp://i.imgur.com/Eqjr2ro.jpg&lt;/a&gt;\n &lt;a href=&quot;\nhttp://i.imgur.com/x2Zu7AM.jpg&quot; rel=&quot;nofollow&quot; target=&quot;_NEW&quot;&gt;\nhttp://i.imgur.com/x2Zu7AM.jpg&lt;/a&gt;","torrent":{"xt":"urn:btih:bf7fec6d11ea3a6fe5dee3014a51e22999ae355f","amp;dn":"Oblivion+%282013%29+3D+BrRip+x264+-+MHDS","amp;tr":["udp%3A%2F%2Ftracker.openbittorrent.com%3A80","udp%3A%2F%2Fopen.demonii.com%3A1337","udp%3A%2F%2Ftracker.coppersurfer.tk%3A6969","udp%3A%2F%2Fexodus.desync.com%3A6969"],"infoHash":"bf7fec6d11ea3a6fe5dee3014a51e22999ae355f","infoHashBuffer":{"type":"Buffer","data":[191,127,236,109,17,234,58,111,229,222,227,1,74,81,226,41,153,174,53,95]},"announce":[],"urlList":[]}}