{"title":"Der Swinger Club GERMAN","uid":11019067,"size":1000228155,"categoryP":"porn","categoryS":"movies","magnet":"?xt=urn:btih:c2fa6047aff5aad6bd72043ceb6bfa23f6b088ad&amp;dn=Der+Swinger+Club+GERMAN&amp;tr=udp%3A%2F%2Ftracker.openbittorrent.com%3A80&amp;tr=udp%3A%2F%2Fopen.demonii.com%3A1337&amp;tr=udp%3A%2F%2Ftracker.coppersurfer.tk%3A6969&amp;tr=udp%3A%2F%2Fexodus.desync.com%3A6969","seeders":4,"leechers":1,"uploader":"digital_ripper","files":1,"time":1410543178,"description":"screens &lt;a href=&quot;\nhttp://www.mypornimage.com/adultimage/uCf&quot; rel=&quot;nofollow&quot; target=&quot;_NEW&quot;&gt;\nhttp://www.mypornimage.com/adultimage/uCf&lt;/a&gt; &lt;a href=&quot;\nhttp://www.mypornimage.com/adultimage/uCL&quot; rel=&quot;nofollow&quot; target=&quot;_NEW&quot;&gt;\nhttp://www.mypornimage.com/adultimage/uCL&lt;/a&gt;\n\n\n\n~~~~~~~~~~~~~~~~~~~~~~~~~~~~~~~~~~~~~~~~~~~~~~~~~~~~~~~~~~~~~~~~~~~~~~~~~~~~~~~\n\n                       ````````````````````````````````\n      Downloads your favourite porn movies only from digital_ripper accounts\n~~~~~~~~~~~~~~~~~~~~~~~~~~~~~~~~~~~~~~~~~~~~~~~~~~~~~~~~~~~~~~~~~~~~~~~~~~~~~~~","torrent":{"xt":"urn:btih:c2fa6047aff5aad6bd72043ceb6bfa23f6b088ad","amp;dn":"Der+Swinger+Club+GERMAN","amp;tr":["udp%3A%2F%2Ftracker.openbittorrent.com%3A80","udp%3A%2F%2Fopen.demonii.com%3A1337","udp%3A%2F%2Ftracker.coppersurfer.tk%3A6969","udp%3A%2F%2Fexodus.desync.com%3A6969"],"infoHash":"c2fa6047aff5aad6bd72043ceb6bfa23f6b088ad","infoHashBuffer":{"type":"Buffer","data":[194,250,96,71,175,245,170,214,189,114,4,60,235,107,250,35,246,176,136,173]},"announce":[],"urlList":[]}}