{"title":"Shantal - The Brazilian Beauty Queen with a King-sized Dick [.fl","uid":9567759,"size":469820646,"categoryP":"porn","categoryS":"movie_clips","magnet":"?xt=urn:btih:d2da561a27aeb7a36ed11e57fee69801b70898bc&amp;dn=Shantal+-+The+Brazilian+Beauty+Queen+with+a+King-sized+Dick+%5B.fl&amp;tr=udp%3A%2F%2Ftracker.openbittorrent.com%3A80&amp;tr=udp%3A%2F%2Fopen.demonii.com%3A1337&amp;tr=udp%3A%2F%2Ftracker.coppersurfer.tk%3A6969&amp;tr=udp%3A%2F%2Fexodus.desync.com%3A6969","seeders":4,"leechers":0,"uploader":"xxxlavalxxx","files":10,"time":1391552389,"description":"Snap out of the dream - Shantal is real! Hope you'll forgive the video quality which isn't as rewarding as the action going on in the scenes.\n\n &lt;a href=&quot;\nhttp://imgdone.com/viewer.php?file=39458288761378112612.jpg&quot; rel=&quot;nofollow&quot; target=&quot;_NEW&quot;&gt;\nhttp://imgdone.com/viewer.php?file=39458288761378112612.jpg&lt;/a&gt;\n    \t\n &lt;a href=&quot;\nhttp://imgdone.com/viewer.php?file=41801297487162860158.jpg&quot; rel=&quot;nofollow&quot; target=&quot;_NEW&quot;&gt;\nhttp://imgdone.com/viewer.php?file=41801297487162860158.jpg&lt;/a&gt;\n    \t &lt;a href=&quot;\nhttp://imgdone.com/viewer.php?file=31984967198099166531.jpg&quot; rel=&quot;nofollow&quot; target=&quot;_NEW&quot;&gt;\nhttp://imgdone.com/viewer.php?file=31984967198099166531.jpg&lt;/a&gt;\n    \t &lt;a href=&quot;\nhttp://imgdone.com/viewer.php?file=60572057345005644782.jpg&quot; rel=&quot;nofollow&quot; target=&quot;_NEW&quot;&gt;\nhttp://imgdone.com/viewer.php?file=60572057345005644782.jpg&lt;/a&gt;\n    \t &lt;a href=&quot;\nhttp://imgdone.com/viewer.php?file=26646844895861258600.jpg&quot; rel=&quot;nofollow&quot; target=&quot;_NEW&quot;&gt;\nhttp://imgdone.com/viewer.php?file=26646844895861258600.jpg&lt;/a&gt;","torrent":{"xt":"urn:btih:d2da561a27aeb7a36ed11e57fee69801b70898bc","amp;dn":"Shantal+-+The+Brazilian+Beauty+Queen+with+a+King-sized+Dick+%5B.fl","amp;tr":["udp%3A%2F%2Ftracker.openbittorrent.com%3A80","udp%3A%2F%2Fopen.demonii.com%3A1337","udp%3A%2F%2Ftracker.coppersurfer.tk%3A6969","udp%3A%2F%2Fexodus.desync.com%3A6969"],"infoHash":"d2da561a27aeb7a36ed11e57fee69801b70898bc","infoHashBuffer":{"type":"Buffer","data":[210,218,86,26,39,174,183,163,110,209,30,87,254,230,152,1,183,8,152,188]},"announce":[],"urlList":[]}}