{"title":"Friends complete DVDRip Season 1-10","uid":4015365,"size":47252470801,"categoryP":"video","categoryS":"tv_shows","magnet":"?xt=urn:btih:d69f42d84e828622588642e0e94ce0c7442b9763&amp;dn=Friends+complete+DVDRip+Season+1-10&amp;tr=udp%3A%2F%2Ftracker.openbittorrent.com%3A80&amp;tr=udp%3A%2F%2Fopen.demonii.com%3A1337&amp;tr=udp%3A%2F%2Ftracker.coppersurfer.tk%3A6969&amp;tr=udp%3A%2F%2Fexodus.desync.com%3A6969","seeders":4,"leechers":0,"uploader":"pliplop8414","files":234,"time":1202328081,"description":"Complete Friends DVDRip-Box ! Very Hot !","torrent":{"xt":"urn:btih:d69f42d84e828622588642e0e94ce0c7442b9763","amp;dn":"Friends+complete+DVDRip+Season+1-10","amp;tr":["udp%3A%2F%2Ftracker.openbittorrent.com%3A80","udp%3A%2F%2Fopen.demonii.com%3A1337","udp%3A%2F%2Ftracker.coppersurfer.tk%3A6969","udp%3A%2F%2Fexodus.desync.com%3A6969"],"infoHash":"d69f42d84e828622588642e0e94ce0c7442b9763","infoHashBuffer":{"type":"Buffer","data":[214,159,66,216,78,130,134,34,88,134,66,224,233,76,224,199,68,43,151,99]},"announce":[],"urlList":[]}}