{"title":"ePSXe 1.7.0 Playstation 1 Emulator fully loaded and ready to go","uid":6142205,"size":6811972,"categoryP":"applications","categoryS":"windows","magnet":"?xt=urn:btih:d8c94b4d6a0ce2d8a2fe57790e88c4be29abd742&amp;dn=ePSXe+1.7.0+Playstation+1+Emulator+fully+loaded+and+ready+to+go&amp;tr=udp%3A%2F%2Ftracker.openbittorrent.com%3A80&amp;tr=udp%3A%2F%2Fopen.demonii.com%3A1337&amp;tr=udp%3A%2F%2Ftracker.coppersurfer.tk%3A6969&amp;tr=udp%3A%2F%2Fexodus.desync.com%3A6969","seeders":5,"leechers":0,"uploader":"DJSS","files":33,"time":1296546837,"description":"THIS TORRENT HAS NO GAMES WHATSOEVER.\nTHIS TORRENT HAS NO GAMES WHATSOEVER.\nTHIS TORRENT HAS NO GAMES WHATSOEVER.\n\nThis is a package with ePSXe 1.7.0 all ready to go.\nIncluded in torrent:\n\nePSXe 1.7.0 core files\nePSXeCutor 1.0.6.0 configuration GUI\nSCPH1001.BIN - Playstation 1 BIOS\nzLib data compression library\n\nWith the following plugins:\n\nVideo\nE}I{'s Soft Driver 0.98\nE}I{'s Soft Driver K6/P1MMX 0.98\nKazzuya Software Driver 1.8\nLewpy's 3dfx/Glide3 GPU 1.42\nP.E.Op.S. Soft Driver 1.18\nPete's D3D Driver 1.77\nPete's DX6 D3D Driver 1.77\n[Next3D] 1.5\n[NextGL] 1.12\n\nAudio\nAndy's SPU Audio Driver 0.16\nePSXe SPU core 1.7.0\nEternal SPU Plugin 1.50\n\nCDROM\nePSXe CDR ASPI core 1.7.0\nePSXe CDR WNT/W2K core 1.7.0\n\nNetplay\nCyberPad 1.3\nKaillera Client \n\n\nHave fun!\n\nTHIS TORRENT HAS NO GAMES WHATSOEVER.\nTHIS TORRENT HAS NO GAMES WHATSOEVER.\nTHIS TORRENT HAS NO GAMES WHATSOEVER.","torrent":{"xt":"urn:btih:d8c94b4d6a0ce2d8a2fe57790e88c4be29abd742","amp;dn":"ePSXe+1.7.0+Playstation+1+Emulator+fully+loaded+and+ready+to+go","amp;tr":["udp%3A%2F%2Ftracker.openbittorrent.com%3A80","udp%3A%2F%2Fopen.demonii.com%3A1337","udp%3A%2F%2Ftracker.coppersurfer.tk%3A6969","udp%3A%2F%2Fexodus.desync.com%3A6969"],"infoHash":"d8c94b4d6a0ce2d8a2fe57790e88c4be29abd742","infoHashBuffer":{"type":"Buffer","data":[216,201,75,77,106,12,226,216,162,254,87,121,14,136,196,190,41,171,215,66]},"announce":[],"urlList":[]}}