{"title":"JAV MRT-011  Amateur Gangbang Plan. Eleven","uid":11826368,"size":3714900755,"categoryP":"porn","categoryS":"hd___movies","magnet":"?xt=urn:btih:fe3f2e8b4d7b0d6bb00bebd6c0b5d8085e7ce005&amp;dn=JAV+MRT-011++Amateur+Gangbang+Plan.+Eleven&amp;tr=udp%3A%2F%2Ftracker.openbittorrent.com%3A80&amp;tr=udp%3A%2F%2Fopen.demonii.com%3A1337&amp;tr=udp%3A%2F%2Ftracker.coppersurfer.tk%3A6969&amp;tr=udp%3A%2F%2Fexodus.desync.com%3A6969","seeders":5,"leechers":2,"uploader":"parkolog","files":1,"time":1429511022,"description":"ID:MRT-011\nRelease Date:2015-04-22\nLength:125 min(s)\nDirector:----\nMaker:Prestige  \nLabel:Moratorium  \nGenre(s):Other FetishAmateurGangbang\nCast:\n\n\nScreens:\n &lt;a href=&quot;\nhttp://en.javseeds.com/images/view/8413032_4194.jpg&quot; rel=&quot;nofollow&quot; target=&quot;_NEW&quot;&gt;\nhttp://en.javseeds.com/images/view/8413032_4194.jpg&lt;/a&gt; &lt;a href=&quot;\nhttp://en.javseeds.com/images/view/3097437_5060.jpg&quot; rel=&quot;nofollow&quot; target=&quot;_NEW&quot;&gt;\nhttp://en.javseeds.com/images/view/3097437_5060.jpg&lt;/a&gt;","torrent":{"xt":"urn:btih:fe3f2e8b4d7b0d6bb00bebd6c0b5d8085e7ce005","amp;dn":"JAV+MRT-011++Amateur+Gangbang+Plan.+Eleven","amp;tr":["udp%3A%2F%2Ftracker.openbittorrent.com%3A80","udp%3A%2F%2Fopen.demonii.com%3A1337","udp%3A%2F%2Ftracker.coppersurfer.tk%3A6969","udp%3A%2F%2Fexodus.desync.com%3A6969"],"infoHash":"fe3f2e8b4d7b0d6bb00bebd6c0b5d8085e7ce005","infoHashBuffer":{"type":"Buffer","data":[254,63,46,139,77,123,13,107,176,11,235,214,192,181,216,8,94,124,224,5]},"announce":[],"urlList":[]}}