{"title":"FSFlyingSchool_Pro_2015_P3D_Setupv400","uid":11745990,"size":96801221,"categoryP":"games","categoryS":"pc","magnet":"?xt=urn:btih:ffb26670d6f8db16180ef7ee1917cccb9b493a96&amp;dn=FSFlyingSchool_Pro_2015_P3D_Setupv400&amp;tr=udp%3A%2F%2Ftracker.openbittorrent.com%3A80&amp;tr=udp%3A%2F%2Fopen.demonii.com%3A1337&amp;tr=udp%3A%2F%2Ftracker.coppersurfer.tk%3A6969&amp;tr=udp%3A%2F%2Fexodus.desync.com%3A6969","seeders":5,"leechers":0,"uploader":"kandoit","files":2,"time":1426020098,"description":"this is for prepar3d only\n\np3d fsflyingschool pro 2015 happy flying","torrent":{"xt":"urn:btih:ffb26670d6f8db16180ef7ee1917cccb9b493a96","amp;dn":"FSFlyingSchool_Pro_2015_P3D_Setupv400","amp;tr":["udp%3A%2F%2Ftracker.openbittorrent.com%3A80","udp%3A%2F%2Fopen.demonii.com%3A1337","udp%3A%2F%2Ftracker.coppersurfer.tk%3A6969","udp%3A%2F%2Fexodus.desync.com%3A6969"],"infoHash":"ffb26670d6f8db16180ef7ee1917cccb9b493a96","infoHashBuffer":{"type":"Buffer","data":[255,178,102,112,214,248,219,22,24,14,247,238,25,23,204,203,155,73,58,150]},"announce":[],"urlList":[]}}